{"status":"OK","id":124,"print_date":"2023-10-13","editor":"Wyna Liu","categories":[{"title":"BEANS","cards":[{"content":"FAVA","position":14},{"content":"KIDNEY","position":11},{"content":"LIMA","position":1},{"content":"PINTO","position":6}]},{"title":"CITIES BEGINNING WITH “L”","cards":[{"content":"LAGOS","position":10},{"content":"LIMERICK","position":3},{"content":"LINCOLN","position":4},{"content":"LUXOR","position":12}]},{"title":"POETRY TERMS","cards":[{"content":"LINE","position":0},{"content":"METER","position":15},{"content":"RHYME","position":9},{"content":"VERSE","position":7}]},{"title":"“THE(E) ___” RAPPERS","cards":[{"content":"CREATOR","position":2},{"content":"DUDE","position":13},{"content":"RAPPER","position":5},{"content":"STALLION","position":8}]}]}