{"status":"OK","id":1207,"print_date":"2026-07-04","editor":"Wyna Liu","categories":[{"title":"PERSIST","cards":[{"content":"CONTINUE","position":13},{"content":"LAST","position":8},{"content":"LINGER","position":0},{"content":"STAY","position":11}]},{"title":"KINDS OF POEMS","cards":[{"content":"BALLAD","position":12},{"content":"EPIC","position":2},{"content":"ODE","position":5},{"content":"VILLANELLE","position":15}]},{"title":"TROPICAL DRINKS","cards":[{"content":"HURRICANE","position":9},{"content":"PAINKILLER","position":14},{"content":"SCORPION","position":7},{"content":"ZOMBIE","position":4}]},{"title":"SWEET ___","cards":[{"content":"DREAMS","position":3},{"content":"NOTHINGS","position":10},{"content":"PEA","position":6},{"content":"SPOT","position":1}]}]}