{"status":"OK","id":1149,"print_date":"2026-05-16","editor":"Wyna Liu","categories":[{"title":"GLASSWARE","cards":[{"content":"COUPE","position":14},{"content":"FLUTE","position":4},{"content":"STEIN","position":9},{"content":"TUMBLER","position":11}]},{"title":"MESS AROUND (WITH)","cards":[{"content":"FIDDLE","position":3},{"content":"MESS","position":6},{"content":"PLAY","position":2},{"content":"TINKER","position":12}]},{"title":"MUSIC PERFORMANCE DIRECTIONS","cards":[{"content":"ALLEGRO","position":15},{"content":"FORTE","position":5},{"content":"LARGO","position":10},{"content":"PIANO","position":1}]},{"title":"ENDING IN SYNONYMS FOR \"ASAP\"","cards":[{"content":"BASSOON","position":7},{"content":"BELFAST","position":8},{"content":"NESQUICK","position":13},{"content":"THERMOSTAT","position":0}]}]}