{"status":"OK","id":1204,"print_date":"2026-07-05","editor":"Wyna Liu","categories":[{"title":"GRANOLA INGREDIENTS","cards":[{"content":"HONEY","position":7},{"content":"NUTS","position":14},{"content":"OATS","position":1},{"content":"SEEDS","position":11}]},{"title":"PAYMENT METHODS","cards":[{"content":"CARD","position":5},{"content":"CASH","position":12},{"content":"CHECK","position":10},{"content":"WIRE","position":3}]},{"title":"AMEX CARD TYPES","cards":[{"content":"CENTURION","position":15},{"content":"GOLD","position":8},{"content":"GREEN","position":2},{"content":"PLATINUM","position":13}]},{"title":"WHAT \"W\" MIGHT STAND FOR","cards":[{"content":"TUNGSTEN","position":9},{"content":"WEST","position":4},{"content":"WIN","position":0},{"content":"WITH","position":6}]}]}