{"status":"OK","id":213,"print_date":"2024-01-07","editor":"Wyna Liu","categories":[{"title":"TECH COMPANIES","cards":[{"content":"ALPHABET","position":12},{"content":"AMAZON","position":15},{"content":"APPLE","position":6},{"content":"META","position":0}]},{"title":"KINDS OF EXAMS","cards":[{"content":"BAR","position":9},{"content":"FINAL","position":11},{"content":"ORAL","position":14},{"content":"PHYSICAL","position":1}]},{"title":"SOMETHING EXEMPLARY","cards":[{"content":"BEAUTY","position":3},{"content":"GEM","position":10},{"content":"MARVEL","position":13},{"content":"PEACH","position":4}]},{"title":"___ TOOTH","cards":[{"content":"BABY","position":5},{"content":"EYE","position":7},{"content":"SWEET","position":8},{"content":"WISDOM","position":2}]}]}