{"status":"OK","id":259,"print_date":"2024-02-21","editor":"Wyna Liu","categories":[{"title":"PESTERS","cards":[{"content":"BADGERS","position":7},{"content":"BUGS","position":2},{"content":"HOUNDS","position":4},{"content":"NAGS","position":15}]},{"title":"TONY WINNERS FOR BEST MUSICAL","cards":[{"content":"ANNIE","position":12},{"content":"CABARET","position":10},{"content":"CATS","position":5},{"content":"COMPANY","position":3}]},{"title":"THEY HAVE KEYS","cards":[{"content":"COMPUTER","position":1},{"content":"PIANO","position":9},{"content":"SUPER","position":0},{"content":"TESTS","position":14}]},{"title":"SCHOOL OF ___","cards":[{"content":"FISH","position":6},{"content":"HARD KNOCKS","position":8},{"content":"ROCK","position":11},{"content":"THOUGHT","position":13}]}]}