{"status":"OK","id":366,"print_date":"2024-05-22","editor":"Wyna Liu","categories":[{"title":"BODY PARTS IN “HEAD, SHOULDERS, KNEES AND TOES”","cards":[{"content":"HEAD","position":8},{"content":"KNEES","position":3},{"content":"SHOULDERS","position":6},{"content":"TOES","position":14}]},{"title":"CAR, INFORMALLY","cards":[{"content":"AUTO","position":12},{"content":"RIDE","position":7},{"content":"WHEELS","position":0},{"content":"WHIP","position":9}]},{"title":"REMOVES THE COVERING OF","cards":[{"content":"PARES","position":15},{"content":"PEELS","position":1},{"content":"SHELLS","position":4},{"content":"SHUCKS","position":10}]},{"title":"“BUZZY” THINGS","cards":[{"content":"BEES","position":2},{"content":"CAFFEINE","position":11},{"content":"GOSSIP","position":5},{"content":"INTERCOMS","position":13}]}]}