{"status":"OK","id":313,"print_date":"2024-04-12","editor":"Wyna Liu","categories":[{"title":"ORDERLY","cards":[{"content":"CLEAN","position":11},{"content":"NEAT","position":6},{"content":"TIDY","position":12},{"content":"TRIM","position":15}]},{"title":"AUGMENTATIVE PREFIXES","cards":[{"content":"HYPER","position":8},{"content":"SUPER","position":0},{"content":"UBER","position":7},{"content":"ULTRA","position":13}]},{"title":"BECOME LARGER","cards":[{"content":"BALLOON","position":1},{"content":"MUSHROOM","position":14},{"content":"SNOWBALL","position":9},{"content":"SWELL","position":3}]},{"title":"ITEMS IN CLASSIC KIDS’ GAMES","cards":[{"content":"DOMINO","position":4},{"content":"JACK","position":5},{"content":"MARBLE","position":10},{"content":"STICK","position":2}]}]}