{"status":"OK","id":364,"print_date":"2024-05-20","editor":"Wyna Liu","categories":[{"title":"SORCERER’S OUTPUT","cards":[{"content":"CHARM","position":8},{"content":"HEX","position":15},{"content":"MAGIC","position":2},{"content":"SPELL","position":13}]},{"title":"ONE BEING MANIPULATED","cards":[{"content":"INSTRUMENT","position":11},{"content":"PAWN","position":9},{"content":"PUPPET","position":1},{"content":"TOOL","position":4}]},{"title":"CLASSIC SUPERHERO WEAR","cards":[{"content":"CAPE","position":6},{"content":"MASK","position":10},{"content":"TIGHTS","position":12},{"content":"UNDERWEAR","position":3}]},{"title":"ACTION MOVIE DIRECTORS","cards":[{"content":"BAY","position":7},{"content":"CARPENTER","position":0},{"content":"SCOTT","position":14},{"content":"WOO","position":5}]}]}