{"status":"OK","id":939,"print_date":"2025-11-19","editor":"Wyna Liu","categories":[{"title":"STOCKY","cards":[{"content":"HUSKY","position":8},{"content":"SOLID","position":7},{"content":"SQUAT","position":0},{"content":"THICK","position":13}]},{"title":"STEER","cards":[{"content":"DIRECT","position":10},{"content":"GUIDE","position":12},{"content":"LEAD","position":5},{"content":"SHEPHERD","position":1}]},{"title":"SECOND WORDS IN POE STORIES, AFTER \"THE\"","cards":[{"content":"CASK","position":9},{"content":"FALL","position":3},{"content":"PIT","position":2},{"content":"MASQUE","position":14}]},{"title":"ORGAN PLUS A LETTER","cards":[{"content":"COLONY","position":11},{"content":"HEARTH","position":15},{"content":"LUNGE","position":4},{"content":"SKINK","position":6}]}]}