{"status":"OK","id":787,"print_date":"2025-06-29","editor":"Wyna Liu","categories":[{"title":"ICE CREAM TREATS","cards":[{"content":"FLOAT","position":1},{"content":"SHAKE","position":8},{"content":"SPLIT","position":13},{"content":"SUNDAE","position":6}]},{"title":"FLINCH","cards":[{"content":"BOLT","position":12},{"content":"JERK","position":15},{"content":"JUMP","position":7},{"content":"STARTLE","position":4}]},{"title":"DANCE MOVES","cards":[{"content":"CABBAGE PATCH","position":14},{"content":"FLOSS","position":11},{"content":"MOONWALK","position":3},{"content":"ROBOT","position":9}]},{"title":"SEEN IN THE AFTERMATH OF A RAINSTORM","cards":[{"content":"EARTHWORM","position":0},{"content":"MUD","position":10},{"content":"MUSHROOM","position":2},{"content":"PUDDLE","position":5}]}]}