{"status":"OK","id":973,"print_date":"2025-12-23","editor":"Wyna Liu","categories":[{"title":"VULNERABILITY","cards":[{"content":"ACHILLES’ HEEL","position":6},{"content":"DOWNFALL","position":12},{"content":"KRYPTONITE","position":3},{"content":"SOFT SPOT","position":9}]},{"title":"FREUDIAN CONCEPTS","cards":[{"content":"FIXATION","position":5},{"content":"OEDIPUS COMPLEX","position":8},{"content":"SUPEREGO","position":15},{"content":"UNCONSCIOUS","position":2}]},{"title":"CHARACTERS IN CAPES","cards":[{"content":"DARTH VADER","position":13},{"content":"DRACULA","position":0},{"content":"LITTLE RED RIDING HOOD","position":10},{"content":"SUPERMAN","position":7}]},{"title":"STARTING WITH SLANG FOR SAUSAGE","cards":[{"content":"BRATZ","position":14},{"content":"DOGMA","position":1},{"content":"FRANKENSTEIN","position":4},{"content":"LINKLATER","position":11}]}]}